pyparc/__init__.py
pyparc/parc.py
pyparc-2.0.4.dist-info/LICENSE.txt
pyparc-2.0.4.dist-info/METADATA
pyparc-2.0.4.dist-info/WHEEL
pyparc-2.0.4.dist-info/top_level.txt
pyparc-2.0.4.dist-info/RECORD
