Metadata-Version: 2.1
Name: pyparc
Version: 2.0.4
Summary: PARC - Piecewise Affine Regression and Classification
Author-email: Alberto Bemporad <alberto.bemporad@imtlucca.it>
Project-URL: Homepage, http://cse.lab.imtlucca.it/~bemporad/parc
Keywords: piecewise linear regression,piecewise linear classification,multivariate regression,multivariate classification,supervised learning
Classifier: Programming Language :: Python :: 3
Classifier: License :: OSI Approved :: Apache Software License
Classifier: Operating System :: OS Independent
Requires-Python: >=3.7
License-File: LICENSE.txt
Requires-Dist: numpy
Requires-Dist: scipy
Requires-Dist: scikit-learn
Requires-Dist: matplotlib
Requires-Dist: pypoman
Requires-Dist: mip
Requires-Dist: faiss-cpu
Requires-Dist: pickle-mixin
